{
  "songs": [
	  {"songName": "Apple (Unused Track)", "init_BeatRate": 8, "init_BeatIntensity": 0.7},
    {"songName": "Graveyard", "video": "graveyard", "skipCountDown": true},
    {"songName": "Romantic Nights", "video": "romantic-nights"},
    {"songName": "hypnospace-is-cool", "video": "hypnospace-is-cool"},
    {"songName": "Living On", "video": "living-on"},
    {"songName": "credits"},
    {"songName": "chaoz-impact"},
    {"songName": "panic"},
    {"songName": "self-aware"},
    {"songName": "the-swatter-song"},
    {"songName": "motorzone"},
    {"songName": "freestyle"},
    {"songName": "battle-vapor"},
    {"songName": "Glacier"},
    {"songName": "heart-of-fire", "init_BeatRate": 8},
    {"songName": "porkrind-shop-electro-swing-remix"},
    {"songName": "disappearance-dj-jo-remix"},
    {"songName": "blackspace-bossrush-sanguine"},
    {"songName": "FNF Pokemon Master"},
    {"songName": "FNF OLD GUILTY"},
    {"songName": "Help Me"},
    {"songName": "it-means-everything-ambient-trance-remix", "shouldResync": false, "video": "it-means-everything-ambient-track", "loopVideo": true},
    {"songName": "it-means-everything-lofi-hiphop-chillhop-remix"},
    {"songName": "Lost Library"},
    {"songName": "monochrome-uptaunt-take"},
    {"songName": "my-time-8-bit", "bgAnimationFPS": 3},
    {"songName": "overhead-hqsg"},
    {"songName": "really-happy-sergrix-remix"},
    {"songName": "fnf-old-reverie"},
    {"songName": "FNF Silent Hills Retaken Sanity"},
    {"songName": "FNF OLD ARISEN TEASER VER"},
    {"songName": "Cold But Warm Winter"}
  ]
}
